{
   "userid":"UCpM3D2v4lvVr59VtRQ8f1JA","username":"Yen Hsiung Tseng","cus_userid":"UCpM3D2v4lvVr59VtRQ8f1JA","cus_username":"Yen Hsiung Tseng","message":"ㄏㄞˉ","time":"1 週前","video_url":"https://youtu.be/8_MpbRWh1jY"
}{
   "userid":"UCpM3D2v4lvVr59VtRQ8f1JA","username":"Yen Hsiung Tseng","cus_userid":"UCpM3D2v4lvVr59VtRQ8f1JA","cus_username":"Yen Hsiung Tseng","message":"嗨","time":"1 週前","video_url":"https://youtu.be/8_MpbRWh1jY"
}{
   "userid":"UCpM3D2v4lvVr59VtRQ8f1JA","username":"Yen Hsiung Tseng","cus_userid":"UCpM3D2v4lvVr59VtRQ8f1JA","cus_username":"Yen Hsiung Tseng","message":"幹","time":"1 週前","video_url":"https://youtu.be/8_MpbRWh1jY"
}{
   "userid":"UC7oTWql8GTUxuhTJCVpR_dw","username":"YuLiang Lin","cus_userid":"UCpM3D2v4lvVr59VtRQ8f1JA","cus_username":"Yen Hsiung Tseng","message":"Test","time":"5 天前","video_url":"https://youtu.be/8_MpbRWh1jY"
}